alexa_browser_client/__init__.py
alexa_browser_client/constants.py
alexa_browser_client/consumers.py
alexa_browser_client/forms.py
alexa_browser_client/helpers.py
alexa_browser_client/views.py
demo/__init__.py
demo/manage.py
demo/views.py
demo/config/__init__.py
demo/config/asgi.py
demo/config/settings.py
demo/config/urls.py
demo/config/wsgi.py
alexa_browser_client-3.3.2.dist-info/LICENSE
alexa_browser_client-3.3.2.dist-info/METADATA
alexa_browser_client-3.3.2.dist-info/WHEEL
alexa_browser_client-3.3.2.dist-info/top_level.txt
alexa_browser_client-3.3.2.dist-info/RECORD
