Metadata-Version: 2.1
Name: alexa-browser-client
Version: 3.3.2
Summary: Alexa client in your browser. Django app.
Home-page: https://github.com/richtier/alexa-browser-client
Author: Richard Tier
License: MIT
Platform: UNKNOWN
Classifier: Development Status :: 4 - Beta
Classifier: Environment :: Web Environment
Classifier: Framework :: Django
Classifier: Framework :: Django :: 2.1
Classifier: Intended Audience :: Developers
Classifier: License :: OSI Approved :: MIT License
Classifier: Natural Language :: English
Classifier: Operating System :: OS Independent
Classifier: Programming Language :: Python :: 3.5
Classifier: Programming Language :: Python :: 3.6
Classifier: Programming Language :: Python :: Implementation :: PyPy
Classifier: Topic :: Software Development :: Libraries :: Python Modules
Requires-Dist: channels (<3.0.0,>=2.1.4)
Requires-Dist: channels-redis (<3.0.0,>=2.1.1)
Requires-Dist: Django (<3.0.0,>=2.1.0)
Requires-Dist: alexa-client (<2.0.0,>=1.4.1)
Requires-Dist: command-lifecycle (<5.0.0,>=4.1.0)
Requires-Dist: requests (<3.0.0,>=2.20.0)
Provides-Extra: test
Requires-Dist: pytest (==3.2.3) ; extra == 'test'
Requires-Dist: pytest-cov (==2.5.1) ; extra == 'test'
Requires-Dist: pytest-django (==3.1.2) ; extra == 'test'
Requires-Dist: pytest-sugar (==0.9.0) ; extra == 'test'
Requires-Dist: flake8 (==3.4.0) ; extra == 'test'
Requires-Dist: codecov (==2.0.9) ; extra == 'test'
Requires-Dist: requests-mock (==1.3.0) ; extra == 'test'
Requires-Dist: django-environ (==0.4.3) ; extra == 'test'
Requires-Dist: pytest-asyncio (==0.9.0) ; extra == 'test'
Requires-Dist: twine (<2.0.0,>=1.11.0) ; extra == 'test'
Requires-Dist: wheel (<1.0.0,>=0.31.0) ; extra == 'test'
Requires-Dist: setuptools (<39.0.0,>=38.6.0) ; extra == 'test'
